LICENSE
MANIFEST.in
README.rst
requirements.txt
setup.py
version.py
alignak_checks_linux_nrpe/__init__.py
alignak_checks_linux_nrpe.egg-info/PKG-INFO
alignak_checks_linux_nrpe.egg-info/SOURCES.txt
alignak_checks_linux_nrpe.egg-info/dependency_links.txt
alignak_checks_linux_nrpe.egg-info/not-zip-safe
alignak_checks_linux_nrpe.egg-info/top_level.txt
alignak_checks_linux_nrpe/etc/arbiter/packs/linux-nrpe/commands.cfg
alignak_checks_linux_nrpe/etc/arbiter/packs/linux-nrpe/groups.cfg
alignak_checks_linux_nrpe/etc/arbiter/packs/linux-nrpe/services.cfg
alignak_checks_linux_nrpe/etc/arbiter/packs/linux-nrpe/templates.cfg
alignak_checks_linux_nrpe/etc/arbiter/packs/resource.d/nrpe.cfg
alignak_checks_linux_nrpe/json/linux-nrpe/commands.json
alignak_checks_linux_nrpe/json/linux-nrpe/hostgroups.json
alignak_checks_linux_nrpe/json/linux-nrpe/hosts-templates.json
alignak_checks_linux_nrpe/json/linux-nrpe/servicegroups.json
alignak_checks_linux_nrpe/json/linux-nrpe/services-templates.json
alignak_checks_linux_nrpe/json/linux-nrpe/setup.sh